README.md
setup.py
text_to_tweets/__init__.py
text_to_tweets.egg-info/PKG-INFO
text_to_tweets.egg-info/SOURCES.txt
text_to_tweets.egg-info/dependency_links.txt
text_to_tweets.egg-info/top_level.txt