Metadata-Version: 2.1
Name: text-to-tweets
Version: 0.1.1
Summary: Split a chunk of text into 280-character blocksAttempting to split at the end of sentences etc.
Home-page: https://github.com/nottrobin/text-to-tweets
Author: Robin Winslow
Author-email: robin@robinwinslow.co.uk
License: UNKNOWN
Platform: UNKNOWN
